csp_lib/__init__.py
csp_lib/__init__.pyi
csp_lib/py.typed
csp_lib/controller/__init__.py
csp_lib/controller/__init__.pyi
csp_lib/controller/protocol.cp313-win_amd64.pyd
csp_lib/controller/protocol.pyi
csp_lib/controller/core/__init__.py
csp_lib/controller/core/__init__.pyi
csp_lib/controller/core/command.cp313-win_amd64.pyd
csp_lib/controller/core/command.pyi
csp_lib/controller/core/context.cp313-win_amd64.pyd
csp_lib/controller/core/context.pyi
csp_lib/controller/core/execution.cp313-win_amd64.pyd
csp_lib/controller/core/execution.pyi
csp_lib/controller/core/strategy.cp313-win_amd64.pyd
csp_lib/controller/core/strategy.pyi
csp_lib/controller/executor/__init__.py
csp_lib/controller/executor/__init__.pyi
csp_lib/controller/executor/strategy_executor.cp313-win_amd64.pyd
csp_lib/controller/executor/strategy_executor.pyi
csp_lib/controller/services/__init__.py
csp_lib/controller/services/__init__.pyi
csp_lib/controller/services/pv_data_service.cp313-win_amd64.pyd
csp_lib/controller/services/pv_data_service.pyi
csp_lib/controller/strategies/__init__.py
csp_lib/controller/strategies/__init__.pyi
csp_lib/controller/strategies/bypass_strategy.cp313-win_amd64.pyd
csp_lib/controller/strategies/bypass_strategy.pyi
csp_lib/controller/strategies/fp_strategy.cp313-win_amd64.pyd
csp_lib/controller/strategies/fp_strategy.pyi
csp_lib/controller/strategies/island_strategy.cp313-win_amd64.pyd
csp_lib/controller/strategies/island_strategy.pyi
csp_lib/controller/strategies/pq_strategy.cp313-win_amd64.pyd
csp_lib/controller/strategies/pq_strategy.pyi
csp_lib/controller/strategies/pv_smooth_strategy.cp313-win_amd64.pyd
csp_lib/controller/strategies/pv_smooth_strategy.pyi
csp_lib/controller/strategies/qv_strategy.cp313-win_amd64.pyd
csp_lib/controller/strategies/qv_strategy.pyi
csp_lib/controller/strategies/schedule_strategy.cp313-win_amd64.pyd
csp_lib/controller/strategies/schedule_strategy.pyi
csp_lib/controller/strategies/stop_strategy.cp313-win_amd64.pyd
csp0924_lib-0.3.1.dist-info/METADATA
csp0924_lib-0.3.1.dist-info/WHEEL
csp0924_lib-0.3.1.dist-info/top_level.txt
csp0924_lib-0.3.1.dist-info/RECORD
