Metadata-Version: 2.4
Name: csp0924_lib
Version: 0.3.1
Summary: CSP Common Library - 模組化工具集
Requires-Python: >=3.13
Requires-Dist: loguru>=0.7.0
Provides-Extra: mongo
Requires-Dist: motor>=3.0.0; extra == "mongo"
Provides-Extra: redis
Requires-Dist: redis>=5.0.0; extra == "redis"
Provides-Extra: modbus
Requires-Dist: pymodbus>=3.0.0; extra == "modbus"
Provides-Extra: all
Requires-Dist: csp0924_lib[modbus,mongo,redis]; extra == "all"
